{
 "custom_fields": [
  {
   "_assign": null,
   "_comments": null,
   "_liked_by": null,
   "_user_tags": null,
   "allow_in_quick_entry": 0,
   "allow_on_submit": 0,
   "bold": 0,
   "collapsible": 0,
   "collapsible_depends_on": null,
   "columns": 0,
   "creation": "2023-02-28 14:31:05.540132",
   "default": null,
   "depends_on": null,
   "description": null,
   "docstatus": 0,
   "dt": "Payroll Entry",
   "fetch_from": null,
   "fetch_if_empty": 0,
   "fieldname": "about_us_team_member",
   "fieldtype": "Link",
   "hidden": 0,
   "hide_border": 0,
   "hide_days": 0,
   "hide_seconds": 0,
   "idx": 36,
   "ignore_user_permissions": 0,
   "ignore_xss_filter": 0,
   "in_global_search": 0,
   "in_list_view": 0,
   "in_preview": 0,
   "in_standard_filter": 0,
   "insert_after": "dimension_col_break",
   "is_system_generated": 1,
   "is_virtual": 0,
   "label": "About Us Team Member",
   "length": 0,
   "mandatory_depends_on": null,
   "modified": "2023-02-28 14:31:05.540132",
   "modified_by": "Administrator",
   "module": null,
   "name": "Payroll Entry-about_us_team_member",
   "no_copy": 0,
   "non_negative": 0,
   "options": "About Us Team Member",
   "owner": "Administrator",
   "permlevel": 0,
   "precision": "",
   "print_hide": 0,
   "print_hide_if_no_value": 0,
   "print_width": null,
   "read_only": 0,
   "read_only_depends_on": null,
   "report_hide": 0,
   "reqd": 0,
   "search_index": 0,
   "sort_options": 0,
   "translatable": 1,
   "unique": 0,
   "width": null
  },
  {
   "_assign": null,
   "_comments": null,
   "_liked_by": null,
   "_user_tags": null,
   "allow_in_quick_entry": 0,
   "allow_on_submit": 0,
   "bold": 0,
   "collapsible": 0,
   "collapsible_depends_on": null,
   "columns": 0,
   "creation": "2023-03-06 12:55:00.947932",
   "default": null,
   "depends_on": null,
   "description": null,
   "docstatus": 0,
   "dt": "Payroll Entry",
   "fetch_from": null,
   "fetch_if_empty": 0,
   "fieldname": "address",
   "fieldtype": "Link",
   "hidden": 0,
   "hide_border": 0,
   "hide_days": 0,
   "hide_seconds": 0,
   "idx": 32,
   "ignore_user_permissions": 0,
   "ignore_xss_filter": 0,
   "in_global_search": 0,
   "in_list_view": 0,
   "in_preview": 0,
   "in_standard_filter": 0,
   "insert_after": "accounting_dimensions_section",
   "is_system_generated": 1,
   "is_virtual": 0,
   "label": "Address",
   "length": 0,
   "mandatory_depends_on": null,
   "modified": "2023-03-06 12:55:00.947932",
   "modified_by": "Administrator",
   "module": null,
   "name": "Payroll Entry-address",
   "no_copy": 0,
   "non_negative": 0,
   "options": "Address",
   "owner": "Administrator",
   "permlevel": 0,
   "precision": "",
   "print_hide": 0,
   "print_hide_if_no_value": 0,
   "print_width": null,
   "read_only": 0,
   "read_only_depends_on": null,
   "report_hide": 0,
   "reqd": 0,
   "search_index": 0,
   "sort_options": 0,
   "translatable": 1,
   "unique": 0,
   "width": null
  },
  {
   "_assign": null,
   "_comments": null,
   "_liked_by": null,
   "_user_tags": null,
   "allow_in_quick_entry": 0,
   "allow_on_submit": 0,
   "bold": 0,
   "collapsible": 0,
   "collapsible_depends_on": null,
   "columns": 0,
   "creation": "2023-03-06 12:58:21.507440",
   "default": null,
   "depends_on": null,
   "description": null,
   "docstatus": 0,
   "dt": "Payroll Entry",
   "fetch_from": null,
   "fetch_if_empty": 0,
   "fieldname": "article",
   "fieldtype": "Link",
   "hidden": 0,
   "hide_border": 0,
   "hide_days": 0,
   "hide_seconds": 0,
   "idx": 33,
   "ignore_user_permissions": 0,
   "ignore_xss_filter": 0,
   "in_global_search": 0,
   "in_list_view": 0,
   "in_preview": 0,
   "in_standard_filter": 0,
   "insert_after": "address",
   "is_system_generated": 1,
   "is_virtual": 0,
   "label": "Article",
   "length": 0,
   "mandatory_depends_on": null,
   "modified": "2023-03-06 12:58:21.507440",
   "modified_by": "Administrator",
   "module": null,
   "name": "Payroll Entry-article",
   "no_copy": 0,
   "non_negative": 0,
   "options": "Article",
   "owner": "Administrator",
   "permlevel": 0,
   "precision": "",
   "print_hide": 0,
   "print_hide_if_no_value": 0,
   "print_width": null,
   "read_only": 0,
   "read_only_depends_on": null,
   "report_hide": 0,
   "reqd": 0,
   "search_index": 0,
   "sort_options": 0,
   "translatable": 1,
   "unique": 0,
   "width": null
  },
  {
   "_assign": null,
   "_comments": null,
   "_liked_by": null,
   "_user_tags": null,
   "allow_in_quick_entry": 0,
   "allow_on_submit": 0,
   "bold": 0,
   "collapsible": 0,
   "collapsible_depends_on": null,
   "columns": 0,
   "creation": "2023-07-19 16:42:59.346562",
   "default": null,
   "depends_on": null,
   "description": null,
   "docstatus": 0,
   "dt": "Payroll Entry",
   "fetch_from": null,
   "fetch_if_empty": 0,
   "fieldname": "validated_attendance_sheet",
   "fieldtype": "Attach",
   "hidden": 0,
   "hide_border": 0,
   "hide_days": 0,
   "hide_seconds": 0,
   "idx": 14,
   "ignore_user_permissions": 0,
   "ignore_xss_filter": 0,
   "in_global_search": 0,
   "in_list_view": 0,
   "in_preview": 0,
   "in_standard_filter": 0,
   "insert_after": "column_break_13",
   "is_system_generated": 0,
   "is_virtual": 0,
   "label": "Validated Attendance Sheet",
   "length": 0,
   "mandatory_depends_on": null,
   "modified": "2023-07-19 16:42:59.346562",
   "modified_by": "Administrator",
   "module": null,
   "name": "Payroll Entry-validated_attendance_sheet",
   "no_copy": 0,
   "non_negative": 0,
   "options": null,
   "owner": "Administrator",
   "permlevel": 0,
   "precision": "",
   "print_hide": 0,
   "print_hide_if_no_value": 0,
   "print_width": null,
   "read_only": 0,
   "read_only_depends_on": null,
   "report_hide": 0,
   "reqd": 0,
   "search_index": 0,
   "sort_options": 0,
   "translatable": 0,
   "unique": 0,
   "width": null
  }
 ],
 "custom_perms": [],
 "doctype": "Payroll Entry",
 "links": [],
 "property_setters": [
  {
   "_assign": null,
   "_comments": null,
   "_liked_by": null,
   "_user_tags": null,
   "creation": "2024-01-24 17:34:48.907234",
   "default_value": null,
   "doc_type": "Payroll Entry",
   "docstatus": 0,
   "doctype_or_field": "DocField",
   "field_name": "salary_slip_based_on_timesheet",
   "idx": 0,
   "is_system_generated": 0,
   "modified": "2024-01-24 17:34:48.907234",
   "modified_by": "Administrator",
   "module": null,
   "name": "Payroll Entry-salary_slip_based_on_timesheet-hidden",
   "owner": "Administrator",
   "property": "hidden",
   "property_type": "Check",
   "row_name": null,
   "value": "1"
  },
  {
   "_assign": null,
   "_comments": null,
   "_liked_by": null,
   "_user_tags": null,
   "creation": "2024-01-04 09:42:32.662642",
   "default_value": null,
   "doc_type": "Payroll Entry",
   "docstatus": 0,
   "doctype_or_field": "DocField",
   "field_name": "end_date",
   "idx": 0,
   "is_system_generated": 0,
   "modified": "2024-01-04 09:42:32.662642",
   "modified_by": "Administrator",
   "module": null,
   "name": "Payroll Entry-end_date-read_only",
   "owner": "Administrator",
   "property": "read_only",
   "property_type": "Check",
   "row_name": null,
   "value": "1"
  },
  {
   "_assign": null,
   "_comments": null,
   "_liked_by": null,
   "_user_tags": null,
   "creation": "2024-01-04 09:42:21.776419",
   "default_value": null,
   "doc_type": "Payroll Entry",
   "docstatus": 0,
   "doctype_or_field": "DocField",
   "field_name": "start_date",
   "idx": 0,
   "is_system_generated": 0,
   "modified": "2024-01-04 09:42:21.776419",
   "modified_by": "Administrator",
   "module": null,
   "name": "Payroll Entry-start_date-read_only",
   "owner": "Administrator",
   "property": "read_only",
   "property_type": "Check",
   "row_name": null,
   "value": "1"
  },
  {
   "_assign": null,
   "_comments": null,
   "_liked_by": null,
   "_user_tags": null,
   "creation": "2024-01-04 09:42:21.623166",
   "default_value": null,
   "doc_type": "Payroll Entry",
   "docstatus": 0,
   "doctype_or_field": "DocType",
   "field_name": null,
   "idx": 0,
   "is_system_generated": 0,
   "modified": "2024-01-04 09:42:21.623166",
   "modified_by": "Administrator",
   "module": null,
   "name": "Payroll Entry-main-field_order",
   "owner": "Administrator",
   "property": "field_order",
   "property_type": "Data",
   "row_name": null,
   "value": "[\"select_payroll_period\", \"posting_date\", \"payroll_frequency\", \"company\", \"column_break_5\", \"currency\", \"exchange_rate\", \"payroll_payable_account\", \"status\", \"section_break_cypo\", \"start_date\", \"end_date\", \"column_break_13\", \"validated_attendance_sheet\", \"salary_slip_based_on_timesheet\", \"deduct_tax_for_unclaimed_employee_benefits\", \"deduct_tax_for_unsubmitted_tax_exemption_proof\", \"employees_tab\", \"section_break_17\", \"branch\", \"department\", \"column_break_21\", \"designation\", \"number_of_employees\", \"section_break_24\", \"employees\", \"section_break_26\", \"validate_attendance\", \"attendance_detail_html\", \"accounting_dimensions_tab\", \"accounting_dimensions_section\", \"address\", \"article\", \"cost_center\", \"dimension_col_break\", \"about_us_team_member\", \"project\", \"account\", \"payment_account\", \"column_break_35\", \"bank_account\", \"salary_slips_created\", \"salary_slips_submitted\", \"failure_details_section\", \"error_message\", \"section_break_41\", \"amended_from\", \"connections_tab\"]"
  }
 ],
 "sync_on_migrate": 1
}