{
 "actions": [],
 "allow_rename": 1,
 "creation": "2023-02-13 17:25:41.520919",
 "doctype": "DocType",
 "editable_grid": 1,
 "engine": "InnoDB",
 "field_order": [
  "company_name",
  "current_round",
  "status"
 ],
 "fields": [
  {
   "fieldname": "company_name",
   "fieldtype": "Data",
   "in_list_view": 1,
   "label": "Company name"
  },
  {
   "fieldname": "current_round",
   "fieldtype": "Data",
   "in_list_view": 1,
   "label": "Current round"
  },
  {
   "fieldname": "status",
   "fieldtype": "Data",
   "in_list_view": 1,
   "label": "Status"
  }
 ],
 "index_web_pages_for_search": 1,
 "istable": 1,
 "links": [],
 "modified": "2023-02-13 17:28:09.289845",
 "modified_by": "Administrator",
 "module": "WSC",
 "name": "Applied Companies",
 "owner": "Administrator",
 "permissions": [],
 "sort_field": "modified",
 "sort_order": "DESC",
 "states": []
}