[
 {
  "docstatus": 0,
  "doctype": "Workflow State",
  "icon": "question-sign",
  "modified": "2021-12-15 11:12:05.156592",
  "name": "Pending",
  "parent": null,
  "parentfield": null,
  "parenttype": null,
  "style": "",
  "workflow_state_name": "Pending"
 },
 {
  "docstatus": 0,
  "doctype": "Workflow State",
  "icon": "ok-sign",
  "modified": "2021-12-15 11:12:05.160346",
  "name": "Approved",
  "parent": null,
  "parentfield": null,
  "parenttype": null,
  "style": "Success",
  "workflow_state_name": "Approved"
 },
 {
  "docstatus": 0,
  "doctype": "Workflow State",
  "icon": "remove",
  "modified": "2021-12-15 11:12:05.163930",
  "name": "Rejected",
  "parent": null,
  "parentfield": null,
  "parenttype": null,
  "style": "Danger",
  "workflow_state_name": "Rejected"
 },
 {
  "docstatus": 0,
  "doctype": "Workflow State",
  "icon": "",
  "modified": "2022-12-05 12:32:12.344704",
  "name": "Draft",
  "parent": null,
  "parentfield": null,
  "parenttype": null,
  "style": "",
  "workflow_state_name": "Draft"
 },
 {
  "docstatus": 0,
  "doctype": "Workflow State",
  "icon": "",
  "modified": "2022-12-05 12:32:49.122162",
  "name": "Approved by Registrar",
  "parent": null,
  "parentfield": null,
  "parenttype": null,
  "style": "",
  "workflow_state_name": "Approved by Registrar"
 },
 {
  "docstatus": 0,
  "doctype": "Workflow State",
  "icon": "",
  "modified": "2022-12-05 12:33:51.038660",
  "name": "Rejected by Registrar",
  "parent": null,
  "parentfield": null,
  "parenttype": null,
  "style": "",
  "workflow_state_name": "Rejected by Registrar"
 },
 {
  "docstatus": 0,
  "doctype": "Workflow State",
  "icon": "",
  "modified": "2022-12-05 12:34:13.214910",
  "name": "Approved by VC",
  "parent": null,
  "parentfield": null,
  "parenttype": null,
  "style": "",
  "workflow_state_name": "Approved by VC"
 },
 {
  "docstatus": 0,
  "doctype": "Workflow State",
  "icon": "",
  "modified": "2022-12-05 12:34:31.292154",
  "name": "Rejected by VC",
  "parent": null,
  "parentfield": null,
  "parenttype": null,
  "style": "",
  "workflow_state_name": "Rejected by VC"
 },
 {
  "docstatus": 0,
  "doctype": "Workflow State",
  "icon": "",
  "modified": "2022-12-05 15:34:54.693216",
  "name": "Approved by COE",
  "parent": null,
  "parentfield": null,
  "parenttype": null,
  "style": "",
  "workflow_state_name": "Approved by COE"
 }
]